growthctl/__init__.py
growthctl/main.py
growthctl/schema.py
growthctl/utils.py
growthctl/providers/__init__.py
growthctl/providers/base.py
growthctl/providers/meta.py
growthctl/providers/mock.py
growthctl-0.1.3.dist-info/METADATA
growthctl-0.1.3.dist-info/WHEEL
growthctl-0.1.3.dist-info/entry_points.txt
growthctl-0.1.3.dist-info/licenses/LICENSE
growthctl-0.1.3.dist-info/RECORD
