Metadata-Version: 2.4
Name: growthctl
Version: 0.1.3
Summary: Marketing as Code - Manage ad campaigns like infrastructure
License-File: LICENSE
Requires-Python: >=3.10
Requires-Dist: facebook-business>=24.0.0
Requires-Dist: pydantic>=2.0.0
Requires-Dist: pyyaml>=6.0.0
Requires-Dist: rich>=14.0.0
Requires-Dist: typer>=0.21.0
